vibelib/__init__.py
vibelib/client.py
vibelib/config.py
vibelib/exceptions.py
vibelib/py.typed
vibelib/operations/__init__.py
vibelib/operations/base.py
vibelib/operations/basic.py
vibelib/operations/lists.py
vibelib/operations/sorting.py
vibelib/operations/strings.py
vibelib-1.0.5.dist-info/licenses/LICENSE
vibelib-1.0.5.dist-info/METADATA
vibelib-1.0.5.dist-info/WHEEL
vibelib-1.0.5.dist-info/top_level.txt
vibelib-1.0.5.dist-info/RECORD
